COPYING
LICENSE
MANIFEST.in
README.md
_yottadb.c
_yottadb.h
pyproject.toml
setup.py
tests/test__yottadb.py
tests/test__yottadb_validation.py
tests/test_fatal_signal.py
tests/test_threeenp1.py
tests/test_wordfreq.py
tests/test_yottadb.py
yottadb/__init__.py
yottadb.egg-info/PKG-INFO
yottadb.egg-info/SOURCES.txt
yottadb.egg-info/dependency_links.txt
yottadb.egg-info/top_level.txt