Metadata-Version: 2.4
Name: yottadb
Version: 2.0.0
Summary: A Pythonic API for accessing YottaDB databases.
Home-page: https://yottadb.com
Author: YottaDB LLC
Author-email: info@yottadb.com
License: GNU Affero General Public License v3
Project-URL: Documentation, https://docs.yottadb.com/MultiLangProgGuide/pythonprogram.html
Project-URL: Source Code, https://gitlab.com/YottaDB/Lang/YDBPython
Project-URL: Issue Tracker, https://gitlab.com/YottaDB/Lang/YDBPython/-/issues
Classifier: License :: OSI Approved :: GNU Affero General Public License v3
Classifier: Programming Language :: Python :: 3
Classifier: Programming Language :: Python :: 3.8
License-File: LICENSE
License-File: COPYING
Dynamic: author
Dynamic: author-email
Dynamic: classifier
Dynamic: description
Dynamic: description-content-type
Dynamic: home-page
Dynamic: license
Dynamic: license-file
Dynamic: project-url
Dynamic: summary
